ndk/__init__.py
ndk/construct.py
ndk/directives.py
ndk/stack.py
ndk/definitions/__init__.py
ndk/definitions/command.py
ndk/definitions/contact.py
ndk/definitions/contactgroup.py
ndk/definitions/host.py
ndk/definitions/hostgroup.py
ndk/definitions/service.py
ndk/definitions/servicegroup.py
ndk/definitions/timeperiod.py
ndk/objects/__init__.py
ndk/objects/command.py
ndk/objects/contact.py
ndk/objects/contactgroup.py
ndk/objects/host.py
ndk/objects/hostgroup.py
ndk/objects/service.py
ndk/objects/servicegroup.py
ndk/objects/timeperiod.py
ndk/options/__init__.py
ndk/options/contact.py
ndk/options/host.py
ndk/options/service.py
tests/__init__.py
tests/definitions/__init__.py
tests/definitions/test_command.py
tests/definitions/test_contact.py
tests/definitions/test_contactgroup.py
tests/definitions/test_hostgroup.py
tests/definitions/test_servicegroup.py
tests/definitions/test_timeperiod.py
tests/objects/__init__.py
tests/objects/test_command.py
tests/objects/test_contact.py
tests/objects/test_contactgroup.py
tests/objects/test_host.py
tests/objects/test_hostgroup.py
tests/objects/test_service.py
tests/objects/test_servicegroup.py
tests/objects/test_timeperiod.py
tests/stack/__init__.py
tests/stack/test_construct.py
tests/stack/test_stack.py
ndk-0.1.0.dist-info/LICENSE
ndk-0.1.0.dist-info/METADATA
ndk-0.1.0.dist-info/WHEEL
ndk-0.1.0.dist-info/top_level.txt
ndk-0.1.0.dist-info/RECORD
