Metadata-Version: 2.1
Name: ndk
Version: 0.1.0
Summary: Nagios Development Kit
Home-page: https://github.com/VunkLai/ndk
Author: Vunk.Lai
Author-email: vunk.lai@gmail.com
License: MIT
Platform: UNKNOWN
Classifier: Programming Language :: Python :: 3
Classifier: License :: OSI Approved :: MIT License
Classifier: Operating System :: OS Independent
Requires-Python: >=3.7
